audioman/__init__.py
audioman/_tags.py
audioman/audio.py
audioman/audio_tags.py
audioman/ffmpeg_commands.py
audioman/format_str.py
audioman/effect/__init__.py
audioman/effect/adjustable_fade.py
audioman/effect/effect.py
audioman-1.1.0.dist-info/LICENSE
audioman-1.1.0.dist-info/METADATA
audioman-1.1.0.dist-info/WHEEL
audioman-1.1.0.dist-info/top_level.txt
audioman-1.1.0.dist-info/RECORD
