Metadata-Version: 2.1
Name: audioman
Version: 1.1.0
Summary: Python library for manipulating audio files. This can be used for editing audio, or tagging audio.
Author: ego-lay-atman-bay
License: GNU GENERAL PUBLIC LICENSE
Project-URL: Homepage, https://github.com/ego-lay-atman-bay/audioman/
Project-URL: Bug Tracker, https://github.com/ego-lay-atman-bay/audioman/issues/
Project-URL: Documentation, https://ego-lay-atman-bay.github.io/audioman/
Classifier: Programming Language :: Python :: 3
Classifier: License :: OSI Approved :: GNU General Public License v3 (GPLv3)
Classifier: Operating System :: OS Independent
Requires-Python: >=3.10
License-File: LICENSE
Requires-Dist: filetype
Requires-Dist: mutagen
Requires-Dist: numpy
Requires-Dist: Pillow
Requires-Dist: setuptools
Requires-Dist: soundfile
